bananagan/__init__.py
bananagan/bananagan.py
bananagan/models/__init__.py
bananagan/models/pix2pixHD/__init__.py
bananagan/models/pix2pixHD/base_model.py
bananagan/models/pix2pixHD/options/__init__.py
bananagan/models/pix2pixHD/options/base_options.py
bananagan/models/pix2pixHD/options/test_options.py
bananagan/models/pix2pixHD/options/train_options.py
bananagan/models/pix2pixHD/pix2pixHD.py
bananagan/models/pix2pixHD/util/__init__.py
bananagan/models/pix2pixHD/util/data_utils.py
bananagan/models/pix2pixHD/util/image_pool.py
bananagan/models/pix2pixHD/util/misc_util.py
bananagan/models/pix2pixHD/util/networks.py
bananagan/utils/__init__.py
bananagan/utils/processing_utils.py
bananagan-0.2.0.dist-info/METADATA
bananagan-0.2.0.dist-info/WHEEL
bananagan-0.2.0.dist-info/RECORD
