Metadata-Version: 2.1
Name: bananagan
Version: 0.2.0
Summary: Python library for generating synthetic images of banana diseases using Generative Adversarial Networks (GANs)
Author: Henry Ruiz
Author-email: henryruiz22@gmail.com
Requires-Python: >=3.10,<4.0
Classifier: Programming Language :: Python :: 3
Classifier: Programming Language :: Python :: 3.10
Classifier: Programming Language :: Python :: 3.11
Classifier: Programming Language :: Python :: 3.12
Requires-Dist: gdown (>=5.2.0,<6.0.0)
Requires-Dist: matplotlib (>=3.9.1,<4.0.0)
Requires-Dist: numpy (>=2.0.1,<3.0.0)
Requires-Dist: opencv-python (>=4.10.0.84,<5.0.0.0)
Requires-Dist: pillow (>=10.4.0,<11.0.0)
Requires-Dist: requests (>=2.32.3,<3.0.0)
Requires-Dist: torch (>=2.3.1,<3.0.0)
Requires-Dist: torchvision (>=0.18.1,<0.19.0)
